barsukov/__init__.py
barsukov/apps/__init__.py
barsukov/apps/change_phase.py
barsukov/apps/lock_in_sim.py
barsukov/apps/colormap/__init__.py
barsukov/apps/colormap/color_map_app.py
barsukov/apps/colormap/color_map_core.py
barsukov/apps/colormap/color_map_widget.py
barsukov/data/__init__.py
barsukov/data/constants.py
barsukov/data/fft.py
barsukov/data/lock_in_sim.py
barsukov/data/noise.py
barsukov/exp/__init__.py
barsukov/exp/exp_utils.py
barsukov/exp/mwHP.py
barsukov/exp/smKE.py
barsukov/sys/__init__.py
barsukov/sys/logger.py
barsukov/sys/saveobj.py
barsukov/sys/script.py
barsukov/sys/time.py
barsukov-1.4.0.dist-info/METADATA
barsukov-1.4.0.dist-info/WHEEL
barsukov-1.4.0.dist-info/top_level.txt
barsukov-1.4.0.dist-info/RECORD
